MANIFEST.in
README.md
setup.py
easy_vqa/__init__.py
easy_vqa/easy_vqa.py
easy_vqa.egg-info/PKG-INFO
easy_vqa.egg-info/SOURCES.txt
easy_vqa.egg-info/dependency_links.txt
easy_vqa.egg-info/top_level.txt
easy_vqa/data/README.md
easy_vqa/data/answers.txt
easy_vqa/data/test/questions.json
easy_vqa/data/test/images/0.png
easy_vqa/data/test/images/1.png
easy_vqa/data/test/images/10.png
easy_vqa/data/test/images/100.png
easy_vqa/data/test/images/101.png
easy_vqa/data/test/images/102.png
easy_vqa/data/test/images/103.png
easy_vqa/data/test/images/104.png
easy_vqa/data/test/images/105.png
easy_vqa/data/test/images/106.png
easy_vqa/data/test/images/107.png
easy_vqa/data/test/images/108.png
easy_vqa/data/test/images/109.png
easy_vqa/data/test/images/11.png
easy_vqa/data/test/images/110.png
easy_vqa/data/test/images/111.png
easy_vqa/data/test/images/112.png
easy_vqa/data/test/images/113.png
easy_vqa/data/test/images/114.png
easy_vqa/data/test/images/115.png
easy_vqa/data/test/images/116.png
easy_vqa/data/test/images/117.png
easy_vqa/data/test/images/118.png
easy_vqa/data/test/images/119.png
easy_vqa/data/test/images/12.png
easy_vqa/data/test/images/120.png
easy_vqa/data/test/images/121.png
easy_vqa/data/test/images/122.png
easy_vqa/data/test/images/123.png
easy_vqa/data/test/images/124.png
easy_vqa/data/test/images/125.png
easy_vqa/data/test/images/126.png
easy_vqa/data/test/images/127.png
easy_vqa/data/test/images/128.png
easy_vqa/data/test/images/129.png
easy_vqa/data/test/images/13.png
easy_vqa/data/test/images/130.png
easy_vqa/data/test/images/131.png
easy_vqa/data/test/images/132.png
easy_vqa/data/test/images/133.png
easy_vqa/data/test/images/134.png
easy_vqa/data/test/images/135.png
easy_vqa/data/test/images/136.png
easy_vqa/data/test/images/137.png
easy_vqa/data/test/images/138.png
easy_vqa/data/test/images/139.png
easy_vqa/data/test/images/14.png
easy_vqa/data/test/images/140.png
easy_vqa/data/test/images/141.png
easy_vqa/data/test/images/142.png
easy_vqa/data/test/images/143.png
easy_vqa/data/test/images/144.png
easy_vqa/data/test/images/145.png
easy_vqa/data/test/images/146.png
