Metadata-Version: 2.1
Name: easy-vqa
Version: 1.0
Summary: The official package for the easy-VQA dataset.
Home-page: http://github.com/vzhou842/easy-VQA
Author: Victor Zhou
Author-email: vzhou842@gmail.com
License: UNKNOWN
Project-URL: Demo, https://easy-vqa-demo.victorzhou.com
Platform: UNKNOWN
Classifier: Development Status :: 5 - Production/Stable
Classifier: Programming Language :: Python :: 3
Classifier: License :: OSI Approved :: MIT License
Classifier: Operating System :: OS Independent
Requires-Python: >=3
